passgen3/__init__.py
passgen3/exceptions.py
passgen3/generate.py
passgen3-0.1.1.dist-info/licenses/LICENSE
passgen3-0.1.1.dist-info/METADATA
passgen3-0.1.1.dist-info/WHEEL
passgen3-0.1.1.dist-info/top_level.txt
passgen3-0.1.1.dist-info/RECORD
