Metadata-Version: 2.4
Name: passgen3
Version: 0.1.1
Summary: Python модуль для генерации пароля
Author-email: Timofey <timofey1166@email.com>
License-Expression: MIT
Project-URL: Homepage, https://github.com/itz-timoxa/passgen3
Project-URL: Repository, https://github.com/itz-timoxa/passgen3
Keywords: generator,password,random
Classifier: Development Status :: 4 - Beta
Classifier: Intended Audience :: Developers
Classifier: Programming Language :: Python :: 3
Classifier: Programming Language :: Python :: 3.6
Classifier: Programming Language :: Python :: 3.7
Classifier: Programming Language :: Python :: 3.8
Classifier: Programming Language :: Python :: 3.9
Classifier: Programming Language :: Python :: 3.10
Classifier: Programming Language :: Python :: 3.11
Classifier: Programming Language :: Python :: 3.12
Classifier: Programming Language :: Python :: 3.13
Classifier: Operating System :: OS Independent
Requires-Python: >=3.6
License-File: LICENSE
Dynamic: license-file
